Adder/half_adder/half_adder.v
module half_adder(a,b,s,c);
input a,b;
output s,c;

//dataflow style uses assign
assign s = a ^ b;
assign c = a & b;
endmodule

Adder/simple_full_adder/full_adder_struct.v
`include "half_adder.v"
module full_adder(a,b,ci,s,co);//{
input a,b,ci;
output s,co;

	//Connection by position (Same order as half_adder.v ports)
	//half_adder u0(a,b,n1,n2);
	//half_adder u1(ci,n1,s,n3);

	//Connection by name (Independent of order)
	half_adder u0(.s(n1),
					.a(a),
					.b(b),
					.c(n2));
	half_adder u1(.a(ci),
				   .s(s),
				   .c(n3),
				   .b(n1)); //Read as half_adder.a, half_adder.b etc

	or(co,n2,n3);

endmodule//}

Adder/simple_full_adder/tb_full_adder.v
//Randomised Input Testbench for Full Adder
`include "full_adder_struct.v"
module tb;//{
	reg a,b,ci;
	wire s,co;
	integer seed;
	//Instantiation (Module name: full_adder, Instance Name: dut)
	full_adder dut (a,b,ci,s,co); //connection by position

	initial begin //Happens once //{
		$dumpfile("output.vcd");
		$dumpvars(0,tb);
		seed = 58897; //To generate random patterns
		repeat(20) begin //{
			a = $random(seed);
			b = $random(seed);
			ci = $random(seed);
			#1;
			$display("%0t: a=%b, b=%b, ci=%b, s=%b, co=%b",$time,a,b,ci,s,co);
			end //}
		end //}
	endmodule //}

Adder/simple_full_adder/output.vcd
$date
	Tue Nov 26 15:12:45 2024
$end
$version
	Icarus Verilog
$end
$timescale
	1s
$end
$scope module tb $end
$var wire 1 ! s $end
$var wire 1 " co $end
$var reg 1 # a $end
$var reg 1 $ b $end
$var reg 1 % ci $end
$var integer 32 & seed [31:0] $end
$scope module dut $end
$var wire 1 # a $end
$var wire 1 $ b $end
$var wire 1 % ci $end
$var wire 1 " co $end
$var wire 1 ! s $end
$var wire 1 ' n3 $end
$var wire 1 ( n2 $end
$var wire 1 ) n1 $end
$scope module u0 $end
$var wire 1 # a $end
$var wire 1 $ b $end
$var wire 1 ( c $end
$var wire 1 ) s $end
$upscope $end
$scope module u1 $end
$var wire 1 % a $end
$var wire 1 ) b $end
$var wire 1 ' c $end
$var wire 1 ! s $end
$upscope $end
$upscope $end
$upscope $end
$enddefinitions $end
$comment Show the parameter values. $end
$dumpall
$end
#0
$dumpvars
0)
0(
0'
b11101110111001011101001100011100 &
1%
0$
0#
0"
1!
$end
#1
1"
0!
1(
0%
1$
1#
b101000100101011111001000011 &
#2
1!
1%
b1100110101101111010101010110110 &
#3
0!
1'
1"
1)
0(
0#
b1110110100011100111101100101 &
#4
1!
0'
0)
1(
1#
b111000100010011011001000000000 &
#5
0"
0!
0(
0%
0$
0#
b10111100011000001001110111110111 &
#6
b11101010001110011010011101111010 &
#7
1!
1%
b111100111100100010101001111001 &
#8
1"
0!
1(
0%
1$
1#
b11101010000100000111010110100100 &
#9
1'
1)
0(
1%
0$
b11100100101010010001000101101011 &
#10
1!
0'
0)
1(
1$
b1001111110001111101001011111110 &
#11
0!
0%
b10101001001011010101101001101 &
#12
0"
0(
0$
0#
b10011011001010101110001000001000 &
#13
1"
1(
1$
1#
b10001001000010110010110010011111 &
#14
1!
0"
1)
0(
0$
b1111111001110011101000101000010 &
#15
0)
1%
0#
b10100001100000111100010111100001 &
#16
1)
0%
1$
b10100011011110000111101100101100 &
#17
1"
0!
1'
1%
0$
1#
b10010110100010111100001110010011 &
#18
0"
1!
0'
0)
0#
b111001110100000000011001000110 &
#19
b1001110100010111010111000110101 &
