Comparator/Comparator_3bit/comparator_1bit_df.v
module comparator_1bit(a, b, gt, eq, lt);
	input a,b;
	output gt, eq, lt;

	//Dataflow style 1
	assign {gt, eq, lt} = (a > b) ? 3'b100 : (a < b) ? 3'b001 : (a == b) ? 3'b010 : 1'bx;//Such coding style used in industry
	//Dataflow style 2
	//assign gt = a&~b;
	//assign lt = ~a&b;
	//assign eq = a~^b; //XNOR

endmodule

Comparator/Comparator_3bit/comparator_3bit_struct.v
//Implement 3-bit comparator using 1-bit comparator
`include "comparator_1bit_df.v"

module comparator_3bit(a, b, gt, eq, lt);
	input[2:0] a,b;
	output gt, eq, lt;
	
	//Instantiate three 1-bit comparators
	
	comparator_1bit u0(a[0], b[0], gt0, eq0, lt0);
	comparator_1bit u1(a[1], b[1], gt1, eq1, lt1);
	comparator_1bit u2(a[2], b[2], gt2, eq2, lt2);


	//Structural Model
//	assign gt = gt2 || (eq2 && gt1) || (eq2 && eq1 && gt0);
//	assign eq = eq2 && eq1 && eq0; 
//	assign lt = lt2 || (eq2 && lt1) || (eq2 && eq1 && lt0);
	
	and(n1, eq2, gt1);
	and(n2, eq2, eq1, gt0);
	or(gt, gt2, n1, n2);
	
	and(eq, eq2, eq1, eq0);

	and(n3, eq2, lt1);
	and(n4, eq2, eq1, lt0);
	or(lt, lt2, n3, n4);

endmodule

Comparator/Comparator_3bit/tb_comparator_3bit.v
`include "comparator_3bit_struct.v"
module tb;//{
	reg [2:0] a,b;
	wire gt, eq, lt;
	integer seed;
	
	comparator_3bit dut(a, b, gt, eq, lt);//Instantiation

	initial begin//{
		$dumpfile("output.vcd");
		$dumpvars(0,tb);
		seed = 69;
		repeat(10)begin//{
		{a,b} = $random(seed);
		#2;
		$display("%0t : a=%b : b=%b : gt=%b : eq=%b : lt=%b",$time, a, b, gt, eq, lt);
		end//}
	end//}
endmodule//}

Comparator/Comparator_3bit/output.vcd
$date
	Thu Nov 28 16:17:04 2024
$end
$version
	Icarus Verilog
$end
$timescale
	1s
$end
$scope module tb $end
$var wire 1 ! lt $end
$var wire 1 " gt $end
$var wire 1 # eq $end
$var reg 3 $ a [2:0] $end
$var reg 3 % b [2:0] $end
$var integer 32 & seed [31:0] $end
$scope module dut $end
$var wire 3 ' a [2:0] $end
$var wire 3 ( b [2:0] $end
$var wire 1 # eq $end
$var wire 1 " gt $end
$var wire 1 ! lt $end
$var wire 1 ) n1 $end
$var wire 1 * n2 $end
$var wire 1 + n3 $end
$var wire 1 , n4 $end
$var wire 1 - lt2 $end
$var wire 1 . lt1 $end
$var wire 1 / lt0 $end
$var wire 1 0 gt2 $end
$var wire 1 1 gt1 $end
$var wire 1 2 gt0 $end
$var wire 1 3 eq2 $end
$var wire 1 4 eq1 $end
$var wire 1 5 eq0 $end
$scope module u0 $end
$var wire 1 6 a $end
$var wire 1 7 b $end
$var wire 1 / lt $end
$var wire 1 2 gt $end
$var wire 1 5 eq $end
$upscope $end
$scope module u1 $end
$var wire 1 8 a $end
$var wire 1 9 b $end
$var wire 1 . lt $end
$var wire 1 1 gt $end
$var wire 1 4 eq $end
$upscope $end
$scope module u2 $end
$var wire 1 : a $end
$var wire 1 ; b $end
$var wire 1 - lt $end
$var wire 1 0 gt $end
$var wire 1 3 eq $end
$upscope $end
$upscope $end
$upscope $end
$enddefinitions $end
$comment Show the parameter values. $end
$dumpall
$end
#0
$dumpvars
0;
0:
09
08
07
06
15
14
13
02
01
00
0/
0.
0-
0,
0+
0*
0)
b0 (
b0 '
b10010001011100001000010 &
b0 %
b0 $
1#
0"
0!
$end
#2
1!
0#
1/
05
1.
04
1-
03
17
19
1;
b111 %
b111 (
b10100011110110001110011011011011 &
#4
1"
1*
14
13
0!
0.
0-
0/
12
16
18
1:
07
b111 $
b111 '
b110 %
b110 (
b11111010001001111110001100000 &
#6
0"
1!
0*
1.
04
1-
03
08
0:
b1 $
b1 '
b10000111011011101111100011100001 &
#8
14
0.
18
b11 $
b11 '
b1111011000011011100100101110 &
#10
1,
13
1!
0-
1/
02
06
08
17
09
0;
b0 $
b0 '
b1 %
b1 (
b110101101001111111010111 &
#12
0!
0,
1"
1.
04
03
10
1:
19
b100 $
b100 '
b11 %
b11 (
b110001110100101110101000101100 &
#14
1+
15
13
0/
1!
0"
0-
00
16
0:
b1 $
b1 '
b10000101111101011100000100111101 &
#16
1/
05
06
b0 $
b0 '
b10000001110110001101011011011010 &
#18
14
0!
0+
1"
0.
0/
12
03
10
16
1:
07
09
b101 $
b101 '
b0 %
b0 (
b11010100011001110001111010010011 &
