Finite_State_Machines/2-bit_saturation_counter/sat_count_2b.v
module sat_count_2b(
	//Inputs
	input clock,
	input reset,
	input decision,

	//Output
	output reg [1:0] status
);

//State Encoding

	localparam STRONGLY_NOT_TAKEN = 2'b00,
			   WEAKLY_NOT_TAKEN = 2'b01,
			   WEAKLY_TAKEN = 2'b10,
			   STRONGLY_TAKEN = 2'b11;

//State Registers
	reg [1:0] currentState;
	reg [1:0] nextState;

//Output
	always@(*) begin
		status = 2'b00; //Default State: STRONGLY NOT TAKEN
		case(currentState)
			WEAKLY_NOT_TAKEN : status = 2'b01;	
			WEAKLY_TAKEN : status = 2'b10;
			STRONGLY_TAKEN : status = 2'b11;
		endcase
	end

//Synchronous state-transition block
	always@(posedge clock or negedge reset) begin //ACTIVE LOW RESET 
		if(!reset) currentState <= STRONGLY_NOT_TAKEN; //Default state after reset
		else currentState <= nextState;
	end

//State transition logic
	always@(*) begin
		case(currentState)
			STRONGLY_NOT_TAKEN : begin
				if(decision) nextState = WEAKLY_NOT_TAKEN;
				else nextState = currentState;
			end
			
			WEAKLY_NOT_TAKEN : begin
				if(decision) nextState = WEAKLY_TAKEN;
				else nextState = STRONGLY_NOT_TAKEN;
			end

			WEAKLY_TAKEN : begin
				if(decision) nextState = STRONGLY_TAKEN;
				else nextState = WEAKLY_NOT_TAKEN;
			end

			STRONGLY_TAKEN : begin
				if(decision) nextState = currentState;
				else nextState = WEAKLY_TAKEN;
			end
		endcase

	end

endmodule

Finite_State_Machines/2-bit_saturation_counter/tb_sat_count.v
`include "sat_count_2b.v"
module tb;
	//Inputs
	reg clk, rst, dcn;
	integer seed;
	//Output
	wire [1:0] stat;
	
	//Parameters for states
	localparam STRONGLY_NOT_TAKEN = 2'b00,
			   WEAKLY_NOT_TAKEN = 2'b01,
			   WEAKLY_TAKEN = 2'b10,
			   STRONGLY_TAKEN = 2'b11;
	
	//Instantiation by name
	sat_count_2b dut(.clock(clk),.reset(rst),.decision(dcn),.status(stat));

	//Clock generation
	initial begin
		clk = 0;
		forever #5 clk = ~clk; //Time period = 10 units
	end
	
	//Applying reset
	initial begin
		rst = 0;//Active Low reset for 2 clock cycles
		@(posedge clk);
		@(posedge clk);
		rst = 1; //Release reset
	end
	
	//Applying inputs
	initial begin
		$dumpfile("out.vcd");
		$dumpvars(0,tb);
		seed = 777;
		repeat(35) begin
			dcn = $random(seed);
			$display("%t :\t RESET = %b :\t CLOCK = %b :\t DECISION = %s :\t STATE = %s",$time,rst,clk,
			dcn == 0 ? "Not Taken": "Taken",
			
			stat == STRONGLY_NOT_TAKEN ? "[STRONGLY NOT TAKEN]":
			stat == WEAKLY_NOT_TAKEN ? "[WEAKLY NOT TAKEN]":
			stat == WEAKLY_TAKEN ? "[WEAKLY TAKEN]":
			stat == STRONGLY_TAKEN ? "[STRONGLY TAKEN]" : " "
			);
			#10;
		end
		$finish;
	end

endmodule

Finite_State_Machines/2-bit_saturation_counter/out.vcd
$date
	Thu Dec 12 17:30:30 2024
$end
$version
	Icarus Verilog
$end
$timescale
	1s
$end
$scope module tb $end
$var wire 2 ! stat [1:0] $end
$var parameter 2 " STRONGLY_NOT_TAKEN $end
$var parameter 2 # STRONGLY_TAKEN $end
$var parameter 2 $ WEAKLY_NOT_TAKEN $end
$var parameter 2 % WEAKLY_TAKEN $end
$var reg 1 & clk $end
$var reg 1 ' dcn $end
$var reg 1 ( rst $end
$var integer 32 ) seed [31:0] $end
$scope module dut $end
$var wire 1 & clock $end
$var wire 1 ' decision $end
$var wire 1 ( reset $end
$var parameter 2 * STRONGLY_NOT_TAKEN $end
$var parameter 2 + STRONGLY_TAKEN $end
$var parameter 2 , WEAKLY_NOT_TAKEN $end
$var parameter 2 - WEAKLY_TAKEN $end
$var reg 2 . currentState [1:0] $end
$var reg 2 / nextState [1:0] $end
$var reg 2 0 status [1:0] $end
$upscope $end
$upscope $end
$enddefinitions $end
$comment Show the parameter values. $end
$dumpall
b10 -
b1 ,
b11 +
b0 *
b10 %
b1 $
b11 #
b0 "
$end
#0
$dumpvars
b0 0
b0 /
b0 .
b11001100101110001100110110 )
0(
0'
0&
b0 !
$end
#5
1&
#10
0&
b1000011111111011000000111111 )
#15
1(
1&
#20
0&
b11111010011100100101010101110100 )
#25
1&
#30
0&
b10110001010110010101000111100101 )
#35
1&
#40
b1 /
0&
1'
b11011111100101000011010101100010 )
#45
b10 /
b1 !
b1 0
b1 .
1&
#50
0&
b11000101110001101011100101111011 )
#55
b11 /
b10 !
b10 0
b10 .
1&
#60
b1 /
0&
0'
b110001000010001100011010000000 )
#65
b0 /
b1 !
b1 0
b1 .
1&
#70
b10 /
0&
1'
b1111100100110110111010010000001 )
#75
b11 /
b10 !
b10 0
b10 .
1&
#80
0&
b100001111001111101100001001110 )
#85
b11 !
b11 0
b11 .
1&
#90
0&
b11000100111100100010110001110111 )
#95
1&
#100
0&
b101110101001101010011001001100 )
#105
1&
#110
b10 /
0&
0'
b1111000001100010000011011011101 )
#115
b1 /
b10 !
b10 0
b10 .
1&
#120
0&
b11000011011110001011011111111010 )
#125
b0 /
b1 !
b1 0
b1 .
1&
#130
b10 /
0&
1'
b1100000111111010000010100110011 )
#135
b11 /
b10 !
b10 0
b10 .
1&
#140
b1 /
0&
0'
b10001001000100111100000011011000 )
#145
b0 /
b1 !
b1 0
b1 .
1&
#150
0&
b10000110011101000110010011111001 )
#155
b0 !
b0 0
b0 .
1&
#160
0&
b11111001010011101000000001100110 )
#165
1&
#170
b1 /
0&
1'
b100000110001111111111110101111 )
#175
b10 /
b1 !
b1 0
b1 .
1&
#180
0&
b1100111110100101010001000100100 )
#185
b11 /
b10 !
b10 0
b10 .
1&
#190
b1 /
0&
0'
b1111000000010111010101011010101 )
#195
b0 /
b1 !
b1 0
b1 .
1&
#200
b10 /
0&
1'
b1100011110110011001110110010010 )
#205
b11 /
b10 !
b10 0
b10 .
1&
#210
0&
b10011111110101011001011111101011 )
#215
b11 !
b11 0
b11 .
1&
#220
0&
b1101110101011001001011000110000 )
#225
1&
#230
b10 /
0&
0'
b11111010000001001011010001110001 )
#235
b1 /
b10 !
b10 0
b10 .
1&
#240
0&
b100111010111110011101101111110 )
#245
b0 /
b1 !
b1 0
b1 .
1&
#250
b10 /
0&
1'
b10011000110001100000100111100111 )
#255
b11 /
b10 !
b10 0
b10 .
1&
#260
0&
b1101110111111011010100011111100 )
#265
b11 !
b11 0
b11 .
1&
#270
0&
b1101011101100010001110111001101 )
#275
1&
#280
b10 /
0&
0'
b1011001001001010100011000101010 )
#285
b1 /
b10 !
b10 0
b10 .
1&
#290
b11 /
0&
1'
b10001101100100110101000110100011 )
#295
b11 !
b11 0
b11 .
1&
#300
0&
b101011110000001010011010001000 )
#305
1&
#310
b10 /
0&
0'
b1111000010000100100001011101001 )
#315
b1 /
b10 !
b10 0
b10 .
1&
#320
0&
b11101101010111100110100110010110 )
#325
b0 /
b1 !
b1 0
b1 .
1&
#330
b10 /
0&
1'
b1001001100011010010101100011111 )
#335
b11 /
b10 !
b10 0
b10 .
1&
#340
b1 /
0&
0'
b111100010110110001101011010100 )
#345
b0 /
b1 !
b1 0
b1 .
1&
