Comparator/comparator_2bit/comparator_2bit_behv.v
module comparator_2bit(a, b, gt, eq, lt);
	input [1:0] a,b; //Declare a and b as 2 bit variables
	output reg gt, eq, lt;
	//Behavioral Style
	always@(*) begin	
		//Initialise the output registers to 0 otherwise they can take garbage values.
		gt = 0;
		lt = 0;
		eq = 0;
		if (a > b)  gt = 1;
		if (b > a)  lt = 1;
		if ( a == b)  eq = 1;
	end
endmodule

Comparator/comparator_2bit/tb_comparator_2bit.v
`include "comparator_2bit_behv.v"
module tb;//{
	reg [1:0] a,b;
	wire gt, eq, lt;
	integer seed;
	
	comparator_2bit dut(a, b, gt, eq, lt);//Instantiation

	initial begin//{
		$dumpfile("output.vcd");
		$dumpvars(0,tb);
		seed = 91;
		repeat(10)begin//{
		{a,b} = $random(seed);
		#2;
		$display("%0t : a=%b : b=%b : gt=%b : eq=%b : lt=%b",$time, a, b, gt, eq, lt);
		end//}
	end//}
endmodule//}

Comparator/comparator_2bit/output.vcd
$date
	Sun Dec 01 13:45:32 2024
$end
$version
	Icarus Verilog
$end
$timescale
	1s
$end
$scope module tb $end
$var wire 1 ! lt $end
$var wire 1 " gt $end
$var wire 1 # eq $end
$var reg 2 $ a [1:0] $end
$var reg 2 % b [1:0] $end
$var integer 32 & seed [31:0] $end
$scope module dut $end
$var wire 2 ' a [1:0] $end
$var wire 2 ( b [1:0] $end
$var reg 1 # eq $end
$var reg 1 " gt $end
$var reg 1 ! lt $end
$upscope $end
$upscope $end
$enddefinitions $end
$comment Show the parameter values. $end
$dumpall
$end
#0
$dumpvars
b0 (
b0 '
b10111111110011111100000 &
b0 %
b0 $
1#
0"
0!
$end
#2
1!
0#
b1 $
b1 '
b10 %
b10 (
b10011011100110000111001100001 &
#4
1!
b0 $
b0 '
b1111001001111100111000010101110 &
#6
1!
b1 $
b1 '
b10110011011001110001000101010111 &
#8
1"
0!
b11 $
b11 '
b1 %
b1 (
b11110110110000010100110110101100 &
#10
1"
b10 %
b10 (
b10110111011010001110111010111101 &
#12
1!
0"
b0 $
b0 '
b11 %
b11 (
b100001111000111100011001011010 &
#14
1#
0!
b1 $
b1 '
b1 %
b1 (
b1111010110100100110100000010011 &
#16
1!
0#
b0 $
b0 '
b11 %
b11 (
b1110001110110010100111000111000 &
#18
1"
0!
b1 $
b1 '
b0 %
b0 (
b10000010001101000111101011011001 &
