Finite_State_Machines/Basic_FSM/Basic_FSM.v
module BasicFSM(
	//Inputs
	input clock,
	input reset,
	input a,
	input b,

	//Outputs
	output wire output_1,
	output wire output_2,
	output wire output_3,
	output wire output_4,
	
	output reg[2:0] status
);

//----------------------------------------------------------------------------

//State Encoding (local parameters to be used only inside module)

	localparam STATE_INITIAL = 3'b000,
			   STATE_1 = 3'b001,
			   STATE_2 = 3'b010,
			   STATE_3 = 3'b011,
			   STATE_4 = 3'b100,
			   STATE_5_PLACEHOLDER = 3'b101,
			   STATE_6_PLACEHOLDER = 3'b110,
			   STATE_7_PLACEHOLDER = 3'b111;

//----------------------------------------------------------------------------

//State Registers
	reg [2:0] currentState;
	reg [2:0] nextState;

//----------------------------------------------------------------------------

//Outputs
//1-bit outputs
	assign output_1 = (currentState == STATE_1);
	assign output_2 = (currentState == STATE_2);
	assign output_3 = (currentState == STATE_3);
	assign output_4 = (currentState == STATE_4);
//Multi-bit outputs (status)
	always@(*) begin
		status = 3'b000;
		case(currentState)
			STATE_1 : status = 3'b001;
			STATE_2 : status = 3'b010;
			STATE_3 : status = 3'b011;
			STATE_4 : status = 3'b100;
		endcase
	end

//----------------------------------------------------------------------------

//Synchronous state-transition block
	always@(posedge clock or posedge reset) begin
		if(reset) currentState <= STATE_INITIAL;
		else currentState <= nextState;
	end

	always @(*)begin //{
		nextState = currentState; //implicit else statement (stay in current state if condition is not satisfied)
		case(currentState)
			STATE_INITIAL : nextState = STATE_1;

			STATE_1 : if(a & b) nextState = STATE_2;

			STATE_2 : if(a) nextState = STATE_3;
		
			STATE_3 : begin
				if(!a & b) nextState = STATE_INITIAL;
				else if(a & !b) nextState = STATE_4;
				end

			STATE_4 : ; 

			STATE_5_PLACEHOLDER : nextState = STATE_INITIAL;

			STATE_6_PLACEHOLDER : nextState = STATE_INITIAL;
		
			STATE_7_PLACEHOLDER : nextState = STATE_INITIAL;

		endcase

	end //}

endmodule

Finite_State_Machines/Basic_FSM/tb_fsm.v
`include "Basic_FSM.v"
module tb;
	reg clk, rst;
	reg p,q;
	integer seed;

	//Outputs
	wire out_1,out_2,out_3,out_4;
	wire [2:0] stat;

	//Instantiation by position
	BasicFSM fsm (.clock(clk),.reset(rst),.a(p),.b(q),.output_1(out_1),.output_2(out_2),.output_3(out_3),.output_4(out_4),.status(stat));

	//Clock generation
	initial begin
		clk = 0;
		forever #5 clk = !clk;
	end

	//Apply reset for 1 posedge
	initial begin
		rst = 1;
		@(posedge clk);
		rst = 0; // Release reset
	end

	//Applying inputs

	initial begin
		$dumpfile("out.vcd");
		$dumpvars(0,tb);
		seed = 457858;
		repeat(30) begin
			{p,q} = $random(seed);
			#5;
    	 	 $display("%t : reset=%b : a=%b : b=%b: clock=%b : Status:%b : Out1=%b : Out2=%b : Out3=%b : Out4=%b ", $time,rst,p,q, clk,stat, out_1,out_2,out_3,out_4);
			//#($urandom_range(5,15));
			
		end
		$finish;
	end
endmodule

Finite_State_Machines/Basic_FSM/out.vcd
$date
	Thu Dec 12 11:29:44 2024
$end
$version
	Icarus Verilog
$end
$timescale
	1s
$end
$scope module tb $end
$var wire 3 ! stat [2:0] $end
$var wire 1 " out_4 $end
$var wire 1 # out_3 $end
$var wire 1 $ out_2 $end
$var wire 1 % out_1 $end
$var reg 1 & clk $end
$var reg 1 ' p $end
$var reg 1 ( q $end
$var reg 1 ) rst $end
$var integer 32 * seed [31:0] $end
$scope module fsm $end
$var wire 1 ' a $end
$var wire 1 ( b $end
$var wire 1 & clock $end
$var wire 1 ) reset $end
$var wire 1 " output_4 $end
$var wire 1 # output_3 $end
$var wire 1 $ output_2 $end
$var wire 1 % output_1 $end
$var parameter 3 + STATE_1 $end
$var parameter 3 , STATE_2 $end
$var parameter 3 - STATE_3 $end
$var parameter 3 . STATE_4 $end
$var parameter 3 / STATE_5_PLACEHOLDER $end
$var parameter 3 0 STATE_6_PLACEHOLDER $end
$var parameter 3 1 STATE_7_PLACEHOLDER $end
$var parameter 3 2 STATE_INITIAL $end
$var reg 3 3 currentState [2:0] $end
$var reg 3 4 nextState [2:0] $end
$var reg 3 5 status [2:0] $end
$upscope $end
$upscope $end
$enddefinitions $end
$comment Show the parameter values. $end
$dumpall
b0 2
b111 1
b110 0
b101 /
b100 .
b11 -
b10 ,
b1 +
$end
#0
$dumpvars
b0 5
b1 4
b0 3
b1011100111011001100111000011011 *
1)
1(
0'
0&
0%
0$
0#
0"
b0 !
$end
#5
b1 !
b1 5
1%
b1 3
b1 4
0)
0(
b111110001100110110101010100000 *
1&
#10
b11010110001101101000001000100001 *
0&
#15
b11010000011000101110000101101110 *
1&
#20
b11000110000011110001101100010111 *
0&
#25
b10 4
1'
1(
b1111001100011111101110001101100 *
1&
#30
b1 4
0'
b10000010110100001111111001111101 *
0&
#35
b1011100110001010010001100011010 *
1&
#40
b10 4
1'
b1101111101111110110110111010011 *
0&
#45
b10 !
b10 5
0%
1$
b10 3
b10 4
0'
b10100010101100011010100011111000 *
1&
#50
b11110110110100001110011010011001 *
0&
#55
b11 4
1'
b100111100101110110110110000110 *
1&
#60
b10 4
0'
0(
b11010010010110001000001001001111 *
0&
#65
b11 4
1'
1(
b1110001110011010101110001000100 *
1&
#70
b11 4
0(
b11101011011001100101011001110101 *
0&
#75
b11 !
b11 5
0$
1#
b11 3
b11 4
1(
b1001110011000010110010110010 *
1&
#80
b100 4
0(
b1100011011101101101010010001011 *
0&
#85
b100 !
b100 5
0#
1"
b100 3
b10000011011111100100001001010000 *
1&
#90
1(
b11110111110010010010101000010001 *
0&
#95
0(
b11001101010010101000110010011110 *
1&
#100
0'
b10111010011101001010000010000111 *
0&
#105
b11011100000100100110011100011100 *
1&
#110
1'
b10010001000101001111110101101101 *
0&
#115
0'
b111100000110100111100101001010 *
1&
#120
1(
b11110010101001011110001001000011 *
0&
#125
1'
b10011101100101101001011010101000 *
1&
#130
b1101101111001010010110010001001 *
0&
#135
0'
0(
b11010000010100001001111010110110 *
1&
#140
1'
b10000111010101000101010110111111 *
0&
#145
0'
1(
b11111100101000100101110011110100 *
1&
